etiniconf/__init__.py
etiniconf/confini_parser.py
etiniconf-0.1.0.dist-info/licenses/LICENSE
etiniconf-0.1.0.dist-info/METADATA
etiniconf-0.1.0.dist-info/WHEEL
etiniconf-0.1.0.dist-info/top_level.txt
etiniconf-0.1.0.dist-info/RECORD
