Metadata-Version: 2.4
Name: etiniconf
Version: 0.1.0
Summary: An INI file parser
Author: Ethan
Author-email: 176188484@qq.com
License: MIT
Classifier: License :: OSI Approved :: MIT License
Classifier: Programming Language :: Python :: 3.9
Requires-Python: >=3.9
License-File: LICENSE
Dynamic: license-file
